<?xml version="1.0" encoding="utf-8"?>
<LevelInformation xmlns:xsi="http://www.w3.org/2001/XMLSchema-instance" xmlns:xsd="http://www.w3.org/2001/XMLSchema">
  <Spawns>
    <SpawnInformation>
      <Name>test</Name>
      <TypeName>DreamWorld.Levels.VillageLevel.Entities.TestEntity</TypeName>
      <Position>
        <X>0</X>
        <Y>-450</Y>
        <Z>-100</Z>
      </Position>
      <Rotation>
        <X>0</X>
        <Y>0</Y>
        <Z>0</Z>
      </Rotation>
      <Scale>
        <X>1</X>
        <Y>1</Y>
        <Z>1</Z>
      </Scale>
    </SpawnInformation>
  </Spawns>
</LevelInformation>